README.md
setup.py
trstemmer/__init__.py
trstemmer/stemmer.py
trstemmer.egg-info/PKG-INFO
trstemmer.egg-info/SOURCES.txt
trstemmer.egg-info/dependency_links.txt
trstemmer.egg-info/requires.txt
trstemmer.egg-info/top_level.txt