Metadata-Version: 2.1
Name: trstemmer
Version: 1.0.0
Summary: A simple Turkish stemmer
Author: Mehmet Utku OZTURK
Author-email: <contact@ælphard.tk>
Keywords: stemmer,machine learning,nlp
Classifier: Development Status :: 3 - Alpha
Classifier: Intended Audience :: Developers
Classifier: Natural Language :: Turkish
Classifier: Programming Language :: Python :: 3
Requires-Python: >3.9.13
